shineflow/ActivationFunction.py
shineflow/Dataset.py
shineflow/Layer.py
shineflow/Model.py
shineflow/NeuralNetwork.py
shineflow/__init__.py
shineflow-0.0.1.dist-info/LICENSE.txt
shineflow-0.0.1.dist-info/METADATA
shineflow-0.0.1.dist-info/WHEEL
shineflow-0.0.1.dist-info/top_level.txt
shineflow-0.0.1.dist-info/RECORD
