Metadata-Version: 2.1
Name: shineflow
Version: 0.0.1
Summary: Feed Forward Neural Networks
Home-page: https://github.com/Subhash3/Neural_Net_Using_NumPy/
Author: Subhash Sarangi
Author-email: subhashsarangi123@gmail.com
License: UNKNOWN
Platform: UNKNOWN
Classifier: Programming Language :: Python :: 3
Classifier: Programming Language :: Python :: 3.6
Classifier: Programming Language :: Python :: 3.7
Classifier: Operating System :: OS Independent
Requires-Python: >=3.6
License-File: LICENSE.txt
Requires-Dist: numpy (>=1.18.1)
Requires-Dist: matplotlib (>=3.1.3)
